README.md
setup.py
aiounittest_tornado/__init__.py
aiounittest_tornado/tornado_app.py
aiounittest_tornado.egg-info/PKG-INFO
aiounittest_tornado.egg-info/SOURCES.txt
aiounittest_tornado.egg-info/dependency_links.txt
aiounittest_tornado.egg-info/top_level.txt