Metadata-Version: 1.0
Name: aiounittest_tornado
Version: 1.0.2
Summary: use aiounittest to test torando with asynico of tornado
Home-page: https://github.com/bigpangl/aio-tornado-test-part
Author: bigpangl
Author-email: bigpangl@163.com
License: UNKNOWN
Platform: UNKNOWN
